lunarz/__init__.py
lunarz/lunar.py
lunarz-0.0.3.dist-info/METADATA
lunarz-0.0.3.dist-info/WHEEL
lunarz-0.0.3.dist-info/entry_points.txt
lunarz-0.0.3.dist-info/top_level.txt
lunarz-0.0.3.dist-info/RECORD
