Metadata-Version: 2.4
Name: lunarz
Version: 0.0.3
Summary: 农历日历工具，支持干支、节气、斋日查询
License: MIT
Requires-Python: >=3.8
Requires-Dist: cnlunar>=0.2.0
